{   "A":"₳",   "a":"₳",   "B":"฿",   "b":"฿",   "C":"₵",   "c":"₵",   "D":"Đ",   "d":"Đ",   "E":"Ɇ",   "e":"Ɇ",   "F":"₣",   "f":"₣",   "G":"₲",   "g":"₲",   "H":"Ⱨ",   "h":"Ⱨ",   "I":"ł",   "i":"ł",   "J":"J",   "j":"J",   "K":"₭",   "k":"₭",   "L":"Ⱡ",   "l":"Ⱡ",   "M":"₥",   "m":"₥",   "N":"₦",   "n":"₦",   "O":"Ø",   "o":"Ø",   "P":"₱",   "p":"₱",   "Q":"Q",   "q":"Q",   "R":"Ɽ",   "r":"Ɽ",   "S":"₴",   "s":"₴",   "T":"₮",   "t":"₮",   "U":"Ʉ",   "u":"Ʉ",   "V":"V",   "v":"V",   "W":"₩",   "w":"₩",   "X":"Ӿ",   "x":"Ӿ",   "Y":"Ɏ",   "y":"Ɏ",   "Z":"Ⱬ",   "z":"Ⱬ", " ":" "  }